<?xml version="1.0" encoding="UTF-8"?>
<objects serializationModel="Studio.02.03.00">
	<object class="AudioFile" id="{8d21c719-b0b3-4856-b5a6-37c6be24bdf1}">
		<property name="assetPath">
			<value>Counter.mp3</value>
		</property>
		<property name="frequencyInKHz">
			<value>44.0999985</value>
		</property>
		<property name="channelCount">
			<value>2</value>
		</property>
		<property name="length">
			<value>5.0677551020408167</value>
		</property>
		<relationship name="masterAssetFolder">
			<destination>{edc35293-a4a0-4d3c-b2f7-7990a28a7e99}</destination>
		</relationship>
	</object>
</objects>
